pathsim/__init__.py
pathsim/_constants.py
pathsim/_version.py
pathsim/connection.py
pathsim/simulation.py
pathsim/subsystem.py
pathsim/blocks/README.md
pathsim/blocks/__init__.py
pathsim/blocks/_block.py
pathsim/blocks/adder.py
pathsim/blocks/amplifier.py
pathsim/blocks/comparator.py
pathsim/blocks/converters.py
pathsim/blocks/counter.py
pathsim/blocks/ctrl.py
pathsim/blocks/delay.py
pathsim/blocks/differentiator.py
pathsim/blocks/dynsys.py
pathsim/blocks/filters.py
pathsim/blocks/fir.py
pathsim/blocks/fmu.py
pathsim/blocks/function.py
pathsim/blocks/integrator.py
pathsim/blocks/kalman.py
pathsim/blocks/lti.py
pathsim/blocks/math.py
pathsim/blocks/multiplier.py
pathsim/blocks/noise.py
pathsim/blocks/ode.py
pathsim/blocks/relay.py
pathsim/blocks/rf.py
pathsim/blocks/rng.py
pathsim/blocks/samplehold.py
pathsim/blocks/scope.py
pathsim/blocks/sources.py
pathsim/blocks/spectrum.py
pathsim/blocks/switch.py
pathsim/blocks/table.py
pathsim/blocks/wrapper.py
pathsim/events/__init__.py
pathsim/events/_event.py
pathsim/events/condition.py
pathsim/events/schedule.py
pathsim/events/zerocrossing.py
pathsim/optim/__init__.py
pathsim/optim/anderson.py
pathsim/optim/booster.py
pathsim/optim/numerical.py
pathsim/optim/operator.py
pathsim/solvers/README.md
pathsim/solvers/__init__.py
pathsim/solvers/_rungekutta.py
pathsim/solvers/_solver.py
pathsim/solvers/bdf.py
pathsim/solvers/dirk2.py
pathsim/solvers/dirk3.py
pathsim/solvers/esdirk32.py
pathsim/solvers/esdirk4.py
pathsim/solvers/esdirk43.py
pathsim/solvers/esdirk54.py
pathsim/solvers/esdirk85.py
pathsim/solvers/euler.py
pathsim/solvers/gear.py
pathsim/solvers/rk4.py
pathsim/solvers/rkbs32.py
pathsim/solvers/rkck54.py
pathsim/solvers/rkdp54.py
pathsim/solvers/rkdp87.py
pathsim/solvers/rkf21.py
pathsim/solvers/rkf45.py
pathsim/solvers/rkf78.py
pathsim/solvers/rkv65.py
pathsim/solvers/ssprk22.py
pathsim/solvers/ssprk33.py
pathsim/solvers/ssprk34.py
pathsim/solvers/steadystate.py
pathsim/utils/__init__.py
pathsim-0.16.1.dist-info/licenses/LICENSE.txt
pathsim-0.16.1.dist-info/METADATA
pathsim-0.16.1.dist-info/WHEEL
pathsim-0.16.1.dist-info/top_level.txt
pathsim-0.16.1.dist-info/RECORD
