Metadata-Version: 2.4
Name: pathsim
Version: 0.16.1
Summary: A differentiable block based hybrid system simulation framework.
Author-email: Milan Rother <milan.rother@gmx.de>
License: MIT
Project-URL: Homepage, https://github.com/pathsim/pathsim
Project-URL: documentation, https://pathsim.readthedocs.io/en/latest/
Keywords: simulation,differentiable,hybrid systems
Classifier: Programming Language :: Python :: 3
Classifier: License :: OSI Approved :: MIT License
Classifier: Operating System :: OS Independent
Requires-Python: >=3.8
License-File: LICENSE.txt
Requires-Dist: numpy>=1.15
Requires-Dist: matplotlib>=3.1
Requires-Dist: scipy>=1.2
Provides-Extra: rf
Requires-Dist: scikit-rf; extra == "rf"
Provides-Extra: test
Requires-Dist: pytest; extra == "test"
Requires-Dist: pytest-cov; extra == "test"
Requires-Dist: codecov; extra == "test"
Requires-Dist: FMPy; extra == "test"
Requires-Dist: scikit-rf; extra == "test"
Provides-Extra: fmi
Requires-Dist: FMPy; extra == "fmi"
Dynamic: license-file
